keystone/__init__.py
keystone/arm64_const.py
keystone/arm_const.py
keystone/evm_const.py
keystone/hexagon_const.py
keystone/keystone.dll
keystone/keystone.py
keystone/keystone_const.py
keystone/mips_const.py
keystone/ppc_const.py
keystone/sparc_const.py
keystone/systemz_const.py
keystone/x86_const.py
keystone_engine_rdv-0.9.3.dist-info/LICENSE.TXT
keystone_engine_rdv-0.9.3.dist-info/METADATA
keystone_engine_rdv-0.9.3.dist-info/WHEEL
keystone_engine_rdv-0.9.3.dist-info/top_level.txt
keystone_engine_rdv-0.9.3.dist-info/RECORD
