Metadata-Version: 2.1
Name: keystone-engine-rdv
Version: 0.9.3
Summary: Keystone assembler engine
Home-page: https://www.keystone-engine.org
Author: Nguyen Anh Quynh
Author-email: aquynh@gmail.com
License: UNKNOWN
Platform: UNKNOWN
Classifier: Development Status :: 5 - Production/Stable
Classifier: Intended Audience :: Developers
Classifier: Topic :: Software Development :: Build Tools
Classifier: License :: OSI Approved :: BSD License
Classifier: Programming Language :: Python :: 2
Classifier: Programming Language :: Python :: 3
Requires: ctypes
Provides: keystone
License-File: LICENSE.TXT
